{">file_transfer>a.bin":">file_transfer",">file_transfer>bc.bin":">file_transfer",">file_transfer>bd.bin":">file_transfer",">scripts>generate_fernet_key.py":">scripts",">scripts>generate_migration.py":">scripts",">scripts>generate_topology.py":">scripts",">scripts>gitlab_test.py":">scripts",">scripts>migration.py":">scripts",">scripts>scalability_migration.py":">scripts",">migrations>rbac_scalability>device.yaml":">migrations>rbac_scalability",">migrations>rbac_scalability>group.yaml":">migrations>rbac_scalability",">migrations>rbac_scalability>link.yaml":">migrations>rbac_scalability",">migrations>rbac_scalability>user.yaml":">migrations>rbac_scalability",">migrations>default>device.yaml":">migrations>default",">migrations>default>link.yaml":">migrations>default",">migrations>default>pool.yaml":">migrations>default",">migrations>default>service.yaml":">migrations>default",">migrations>default>task.yaml":">migrations>default",">migrations>default>user.yaml":">migrations>default",">migrations>default>workflow_edge.yaml":">migrations>default",">services>.gitkeep":">services",">spreadsheets>defaults.xls":">spreadsheets",">spreadsheets>device_counters.xls":">spreadsheets",">spreadsheets>europe.xls":">spreadsheets",">spreadsheets>objects.xls":">spreadsheets",">spreadsheets>topology_20000_nodes_links.xls":">spreadsheets",">spreadsheets>topology_2000_nodes_3000_links.xls":">spreadsheets",">spreadsheets>topology_3000_nodes_6000_links.xls":">spreadsheets",">spreadsheets>topology_500.xls":">spreadsheets",">spreadsheets>topology_65000.xls":">spreadsheets",">spreadsheets>topology_9000.xls":">spreadsheets",">spreadsheets>topology_9000_nodes_links.xls":">spreadsheets",">spreadsheets>usa.xls":">spreadsheets",">spreadsheets>usa_nocoords_sameip.xls":">spreadsheets",">snippets>delete_corrupted_edges.py":">snippets",">snippets>duplicates_in_association_table.py":">snippets",">snippets>empty.py":">snippets",">snippets>functions.py":">snippets",">snippets>getsizeof.py":">snippets",">snippets>memory_profile.py":">snippets",">snippets>sql_performances.py":">snippets",">migrations>examples>credential.yaml":">migrations>examples",">migrations>examples>device.yaml":">migrations>examples",">migrations>examples>group.yaml":">migrations>examples",">migrations>examples>link.yaml":">migrations>examples",">migrations>examples>network.yaml":">migrations>examples",">migrations>examples>pool.yaml":">migrations>examples",">migrations>examples>port.yaml":">migrations>examples",">migrations>examples>service.yaml":">migrations>examples",">migrations>examples>task.yaml":">migrations>examples",">migrations>examples>user.yaml":">migrations>examples",">migrations>examples>workflow_edge.yaml":">migrations>examples",">playbooks>ansible.cfg":">playbooks",">playbooks>arista_show_running_config.yml":">playbooks",">playbooks>arista_show_version.yml":">playbooks",">playbooks>change_hostname.yml":">playbooks",">playbooks>inventory":">playbooks",">playbooks>output.txt":">playbooks",">playbooks>save_running_config.yaml":">playbooks",">playbooks>simple_playbook.yml":">playbooks",">migrations>model_scalability>device.yaml":">migrations>model_scalability",">migrations>model_scalability>group.yaml":">migrations>model_scalability",">migrations>model_scalability>link.yaml":">migrations>model_scalability",">migrations>model_scalability>network.yaml":">migrations>model_scalability",">migrations>model_scalability>pool.yaml":">migrations>model_scalability",">migrations>model_scalability>service.yaml":">migrations>model_scalability",">migrations>model_scalability>task.yaml":">migrations>model_scalability",">migrations>model_scalability>user.yaml":">migrations>model_scalability",">migrations>examples>file.yaml":">migrations>examples",">reports>report_results.j2":">reports",">migrations>default>group.yaml":">migrations>default",">migrations>default>file.yaml":">migrations>default",">migrations>default>network.yaml":">migrations>default",">migrations>default>credential.yaml":">migrations>default",">migrations>small_scalability>credential.yaml":">migrations>small_scalability",">migrations>small_scalability>device.yaml":">migrations>small_scalability",">migrations>small_scalability>file.yaml":">migrations>small_scalability",">migrations>small_scalability>group.yaml":">migrations>small_scalability",">migrations>small_scalability>link.yaml":">migrations>small_scalability",">migrations>small_scalability>network.yaml":">migrations>small_scalability",">migrations>small_scalability>pool.yaml":">migrations>small_scalability",">migrations>small_scalability>service.yaml":">migrations>small_scalability",">migrations>small_scalability>task.yaml":">migrations>small_scalability",">migrations>small_scalability>user.yaml":">migrations>small_scalability",">migrations>small_scalability>workflow_edge.yaml":">migrations>small_scalability",">migrations>examples>metadata.yaml":">migrations>examples"}